pyshortcuts/__init__.py
pyshortcuts/darwin.py
pyshortcuts/debugtimer.py
pyshortcuts/gformat.py
pyshortcuts/linux.py
pyshortcuts/shortcut.py
pyshortcuts/utils.py
pyshortcuts/version.py
pyshortcuts/windows.py
pyshortcuts/wxgui.py
pyshortcuts/icons/ladder.icns
pyshortcuts/icons/ladder.ico
pyshortcuts/icons/ladder.png
pyshortcuts/icons/py.icns
pyshortcuts/icons/py.ico
pyshortcuts-1.9.5.dist-info/LICENSE
pyshortcuts-1.9.5.dist-info/METADATA
pyshortcuts-1.9.5.dist-info/WHEEL
pyshortcuts-1.9.5.dist-info/entry_points.txt
pyshortcuts-1.9.5.dist-info/top_level.txt
pyshortcuts-1.9.5.dist-info/RECORD
