Metadata-Version: 2.1
Name: pyshortcuts
Version: 1.9.5
Summary: Create desktop and Start Menu shortcuts for python scripts
Author-email: Matthew Newville <matt.newville@gmail.com>
License: The MIT License
Project-URL: Homepage, https://github.com/newville/pyshortcuts/
Project-URL: Documentation, https://github.com/newville/pyshortcuts/README.md
Project-URL: Changelog, https://github.com/newville/pyshortcuts/issues
Keywords: desktop shortcuts,python utilities
Classifier: Development Status :: 5 - Production/Stable
Classifier: Intended Audience :: End Users/Desktop
Classifier: Intended Audience :: Developers
Classifier: License :: OSI Approved :: MIT License
Classifier: Operating System :: OS Independent
Classifier: Programming Language :: Python :: 3
Classifier: Programming Language :: Python :: 3 :: Only
Classifier: Programming Language :: Python :: 3.9
Classifier: Programming Language :: Python :: 3.10
Classifier: Programming Language :: Python :: 3.11
Classifier: Programming Language :: Python :: 3.12
Classifier: Programming Language :: Python :: 3.13
Classifier: Programming Language :: Python :: Implementation :: CPython
Classifier: Programming Language :: Python :: Implementation :: PyPy
Requires-Python: >=3.9
License-File: LICENSE
Requires-Dist: charset-normalizer
Requires-Dist: pywin32 ; platform_system == "Windows"
Provides-Extra: all
Requires-Dist: pyshortcuts[dev,doc,gui,test] ; extra == 'all'
Provides-Extra: dev
Requires-Dist: build ; extra == 'dev'
Requires-Dist: twine ; extra == 'dev'
Provides-Extra: doc
Requires-Dist: Sphinx ; extra == 'doc'
Provides-Extra: gui
Requires-Dist: wxPython ; extra == 'gui'
Provides-Extra: test
Requires-Dist: coverage ; extra == 'test'
Requires-Dist: pytest ; extra == 'test'
Requires-Dist: pytest-cov ; extra == 'test'
